snowpenguin/__init__.py
snowpenguin/django/__init__.py
snowpenguin/django/recaptcha2/__init__.py
snowpenguin/django/recaptcha2/fields.py
snowpenguin/django/recaptcha2/tests.py
snowpenguin/django/recaptcha2/widgets.py
snowpenguin/django/recaptcha2/locale/it/LC_MESSAGES/django.mo
snowpenguin/django/recaptcha2/migrations/__init__.py
snowpenguin/django/recaptcha2/templates/snowpenguin/recaptcha/recaptcha_automatic.html
snowpenguin/django/recaptcha2/templates/snowpenguin/recaptcha/recaptcha_explicit.html
snowpenguin/django/recaptcha2/templates/snowpenguin/recaptcha/recaptcha_explicit_support.html
snowpenguin/django/recaptcha2/templates/snowpenguin/recaptcha/recaptcha_init.html
snowpenguin/django/recaptcha2/templates/snowpenguin/recaptcha/recaptcha_invisible_button.html
snowpenguin/django/recaptcha2/templatetags/__init__.py
snowpenguin/django/recaptcha2/templatetags/recaptcha2.py
django_recaptcha2-1.4.1.dist-info/LICENSE
django_recaptcha2-1.4.1.dist-info/METADATA
django_recaptcha2-1.4.1.dist-info/WHEEL
django_recaptcha2-1.4.1.dist-info/top_level.txt
django_recaptcha2-1.4.1.dist-info/RECORD
