Metadata-Version: 1.1
Name: django-recaptcha2
Version: 1.4.1
Summary: Django reCaptcha v2 field/widget
Home-page: https://github.com/kbytesys/django-recaptcha2
Author: Andrea Briganti
Author-email: kbytesys@gmail.com
License: GNU LGPL v2
Download-URL: https://github.com/kbytesys/django-recaptcha2/tarball/v1.4.1
Keywords: django,recaptcha,recaptcha2
Platform: UNKNOWN
Classifier: Development Status :: 5 - Production/Stable
Classifier: Environment :: Web Environment
Classifier: Intended Audience :: Developers
Classifier: License :: OSI Approved :: GNU Lesser General Public License v2 (LGPLv2)
Classifier: Natural Language :: English
Classifier: Programming Language :: Python
Classifier: Programming Language :: Python :: 3
Classifier: Framework :: Django
Classifier: Framework :: Django :: 1.8
Classifier: Framework :: Django :: 1.9
Classifier: Framework :: Django :: 1.10
Classifier: Framework :: Django :: 1.11
Classifier: Framework :: Django :: 2.0
Classifier: Framework :: Django :: 2.1
Classifier: Operating System :: OS Independent
Classifier: Topic :: Internet :: WWW/HTTP
Classifier: Topic :: Software Development :: Libraries :: Python Modules
